halogen/__init__.py
halogen/exceptions.py
halogen/schema.py
halogen/types.py
halogen/validators.py
halogen/vnd/__init__.py
halogen/vnd/error.py
halogen-2.1.1.dist-info/licenses/LICENSE.txt
halogen-2.1.1.dist-info/METADATA
halogen-2.1.1.dist-info/WHEEL
halogen-2.1.1.dist-info/top_level.txt
halogen-2.1.1.dist-info/RECORD
