Metadata-Version: 2.4
Name: halogen
Version: 2.1.1
Summary: Python HAL generation/parsing library
Home-page: https://github.com/paylogic/halogen
Author: Oleg Pidsadnyi, Paylogic International and others
Author-email: developers@paylogic.com
License: MIT license
Classifier: Development Status :: 6 - Mature
Classifier: Intended Audience :: Developers
Classifier: License :: OSI Approved :: MIT License
Classifier: Operating System :: POSIX
Classifier: Operating System :: Microsoft :: Windows
Classifier: Operating System :: MacOS :: MacOS X
Classifier: Topic :: Software Development :: Testing
Classifier: Topic :: Software Development :: Libraries
Classifier: Topic :: Utilities
Classifier: Programming Language :: Python :: 3
Classifier: Programming Language :: Python :: 3.6
Classifier: Programming Language :: Python :: 3.7
Classifier: Programming Language :: Python :: 3.8
Classifier: Programming Language :: Python :: 3.9
Classifier: Programming Language :: Python :: 3.10
Classifier: Programming Language :: Python :: 3.11
Classifier: Programming Language :: Python :: 3.12
Requires-Python: >=3.6
License-File: LICENSE.txt
Requires-Dist: cached-property
Requires-Dist: isodate
Requires-Dist: python-dateutil
Requires-Dist: pytz
Dynamic: author
Dynamic: author-email
Dynamic: classifier
Dynamic: description
Dynamic: home-page
Dynamic: license
Dynamic: license-file
Dynamic: requires-dist
Dynamic: requires-python
Dynamic: summary
